curie/__init__.py
curie/construct_workflow_graph.py
curie/docker_setup.py
curie/experiment.py
curie/formatter.py
curie/generate_report.py
curie/logger.py
curie/main.py
curie/model.py
curie/reporter.py
curie/scheduler.py
curie/settings.py
curie/tool.py
curie/utils.py
curie/modified_deps/__init__.py
curie/modified_deps/langchain_bash/__init__.py
curie/modified_deps/langchain_bash/bash.py
curie/modified_deps/langchain_bash/tool.py
curie/nodes/__init__.py
curie/nodes/analyzer.py
curie/nodes/architect.py
curie/nodes/base_node.py
curie/nodes/concluder.py
curie/nodes/data_analyzer.py
curie/nodes/exec_validator.py
curie/nodes/llm_validator.py
curie/nodes/patcher.py
curie/nodes/technician.py
curie/nodes/user_input.py
curie_ai-0.1.12.dist-info/licenses/LICENSE
curie_ai-0.1.12.dist-info/METADATA
curie_ai-0.1.12.dist-info/WHEEL
curie_ai-0.1.12.dist-info/entry_points.txt
curie_ai-0.1.12.dist-info/top_level.txt
curie_ai-0.1.12.dist-info/RECORD
