Metadata-Version: 2.4
Name: curie-ai
Version: 0.1.12
Summary: A package for scientific research experimentation agent
Home-page: https://github.com/Just-Curieous/Curie
Author: Jiachen Liu
Author-email: amberjcjj@gmail.com
Classifier: Programming Language :: Python :: 3
Classifier: License :: OSI Approved :: Apache Software License
Classifier: Operating System :: OS Independent
Requires-Python: >=3.9
License-File: LICENSE
Requires-Dist: psutil
Requires-Dist: argparse
Requires-Dist: requests
Requires-Dist: platform-utils
Dynamic: author
Dynamic: author-email
Dynamic: classifier
Dynamic: description
Dynamic: description-content-type
Dynamic: home-page
Dynamic: license-file
Dynamic: requires-dist
Dynamic: requires-python
Dynamic: summary
